yuerenge_database_mcp/__init__.py
yuerenge_database_mcp/__main__.py
yuerenge_database_mcp/config/__init__.py
yuerenge_database_mcp/config/config_manager.py
yuerenge_database_mcp/config/database_config.json
yuerenge_database_mcp/config/sample_database_config.json
yuerenge_database_mcp/db_tools/__init__.py
yuerenge_database_mcp/db_tools/connections/__init__.py
yuerenge_database_mcp/db_tools/connections/connection_manager.py
yuerenge_database_mcp/db_tools/connections/database_adapters.py
yuerenge_database_mcp/db_tools/core/__init__.py
yuerenge_database_mcp/db_tools/core/database_manager.py
yuerenge_database_mcp/db_tools/core/exceptions.py
yuerenge_database_mcp/db_tools/database_manager.py
yuerenge_database_mcp/db_tools/db_tools.py
yuerenge_database_mcp/db_tools/formatting/__init__.py
yuerenge_database_mcp/db_tools/formatting/format_manager.py
yuerenge_database_mcp/db_tools/operations/__init__.py
yuerenge_database_mcp/db_tools/operations/async_data_manager.py
yuerenge_database_mcp/db_tools/operations/data_manager.py
yuerenge_database_mcp/db_tools/operations/table_manager.py
yuerenge_database_mcp/db_tools/utils/__init__.py
yuerenge_database_mcp/db_tools/utils/log_manager.py
yuerenge_database_mcp/db_tools/utils/oracle_utils.py
yuerenge_database_mcp/server_lifecycle.py
yuerenge_database_mcp-0.1.6.dist-info/WHEEL
yuerenge_database_mcp-0.1.6.dist-info/entry_points.txt
yuerenge_database_mcp-0.1.6.dist-info/METADATA
yuerenge_database_mcp-0.1.6.dist-info/RECORD
