Metadata-Version: 2.3
Name: yuerenge-database-mcp
Version: 0.1.6
Summary: A database management tool based on the MCP protocol
Author: yuerenge
Author-email: yuerenge <2309814831@qq.com>
Requires-Dist: mcp[cli]>=1.24.0
Requires-Dist: sqlalchemy>=2.0.0
Requires-Dist: pymysql>=1.1.0
Requires-Dist: oracledb>=2.0.0
Requires-Python: >=3.8
